find_a_number_game/cli.py
find_a_number_game/fonts/AGENCYB.TTF
find_a_number_game/fonts/ALGER.TTF
find_a_number_game/fonts/BASKVILL.TTF
find_a_number_game/fonts/BELL.TTF
find_a_number_game/fonts/BOD_PSTC.TTF
find_a_number_game/fonts/BROADW.TTF
find_a_number_game/fonts/CHILLER.TTF
find_a_number_game/fonts/COLONNA.TTF
find_a_number_game/fonts/CURLZ.TTF
find_a_number_game/fonts/ENGR.TTF
find_a_number_game/fonts/ERASBD.TTF
find_a_number_game/fonts/FORTE.TTF
find_a_number_game/fonts/GIGI.TTF
find_a_number_game/fonts/JOKERMAN.TTF
find_a_number_game/fonts/MISTRAL.TTF
find_a_number_game/fonts/OCRAEXT.TTF
find_a_number_game/fonts/ONYX.TTF
find_a_number_game/fonts/PAPYRUS.TTF
find_a_number_game/fonts/PLAYBILL.TTF
find_a_number_game/fonts/PRISTINA.TTF
find_a_number_game/fonts/RAVIE.TTF
find_a_number_game/fonts/STENCIL.TTF
find_a_number_game/fonts/comic.ttf
find_a_number_game/fonts/ebrima.ttf
find_a_number_game-1.0.4.dist-info/LICENSE
find_a_number_game-1.0.4.dist-info/METADATA
find_a_number_game-1.0.4.dist-info/WHEEL
find_a_number_game-1.0.4.dist-info/entry_points.txt
find_a_number_game-1.0.4.dist-info/RECORD
