Metadata-Version: 2.1
Name: find-a-number-game
Version: 1.0.4
Summary: Game that can be played with friends and family!
Keywords: game
Author: Armen Martirosyan
Requires-Python: >=3.7,<4.0
Classifier: Programming Language :: Python :: 3
Classifier: Programming Language :: Python :: 3.7
Classifier: Programming Language :: Python :: 3.8
Classifier: Programming Language :: Python :: 3.9
Classifier: Programming Language :: Python :: 3.10
Classifier: Programming Language :: Python :: 3.11
Classifier: Programming Language :: Python :: 3.12
Classifier: Programming Language :: Python :: 3.13
Requires-Dist: click (>=8.1.8,<9.0.0)
Requires-Dist: reportlab (>=4.2.5,<5.0.0)
Project-URL: Changelog, https://github.com/armartirosyan/find-a-number-game/blob/master/CHANGELOG.md
Project-URL: Homepage, https://github.com/armartirosyan/find-a-number-game
Project-URL: Issues, https://github.com/armartirosyan/find-a-number-game/issues
Project-URL: Repository, https://github.com/armartirosyan/find-a-number-game.git
